qt_async_threads/__init__.py
qt_async_threads/_async_runner_abc.py
qt_async_threads/_qt_async_runner.py
qt_async_threads/_sequential_runner.py
qt_async_threads/py.typed
qt_async_threads/pytest_plugin.py
qt_async_threads-0.6.0.dist-info/LICENSE
qt_async_threads-0.6.0.dist-info/METADATA
qt_async_threads-0.6.0.dist-info/WHEEL
qt_async_threads-0.6.0.dist-info/entry_points.txt
qt_async_threads-0.6.0.dist-info/top_level.txt
qt_async_threads-0.6.0.dist-info/RECORD
