Metadata-Version: 2.1
Name: qt-async-threads
Version: 0.6.0
Summary: Use convenient async/await syntax to spawn threads in Qt applications
Home-page: https://qt-async-threads.readthedocs.io/
Author: Bruno Oliveira
Author-email: nicoddemus@gmail.com
License: MIT
Keywords: qt, async, threads,Source=https://github.com/nicoddemus/qt-async-threads,Docs=https://qt-async-threads.readthedocs.io
Classifier: Development Status :: 4 - Beta
Classifier: Environment :: X11 Applications :: Qt
Classifier: Intended Audience :: Developers
Classifier: License :: OSI Approved :: MIT License
Classifier: Operating System :: MacOS :: MacOS X
Classifier: Operating System :: Microsoft :: Windows
Classifier: Operating System :: POSIX
Classifier: Programming Language :: Python :: 3
Classifier: Topic :: Software Development :: Libraries
Classifier: Topic :: Software Development :: User Interfaces
Classifier: Topic :: Utilities
Requires-Python: >=3.10
License-File: LICENSE
Requires-Dist: attrs
Requires-Dist: boltons
Requires-Dist: qtpy
Provides-Extra: dev
Requires-Dist: black ; extra == 'dev'
Requires-Dist: mypy ; extra == 'dev'
Requires-Dist: pre-commit ; extra == 'dev'
Requires-Dist: pytest-qt ; extra == 'dev'
Requires-Dist: requests ; extra == 'dev'
